{"document": {"sentiment": "negative", "confidence": {"negative": 99.518715, "positive": 0.01114251, "neutral": 0.47014505}}, "sentences": [{"content": "\uc0ac\uc2e4 \ub0b4\uac00 \uc791\ub144\uc5d0 \uad34\ub86d\ud614\ub358 \uce5c\uad6c\uac00 \ud55c \uba85 \uc788\uc5b4.", "offset": 0, "length": 26, "sentiment": "negative", "confidence": {"negative": 0.9430269, "positive": 0.0010024405, "neutral": 0.05597074}, "highlights": [{"offset": 0, "length": 25}]}, {"content": " \uc9c0\uae08 \uc0dd\uac01\ud574\ubcf4\uba74 \uc544\uc8fc \ubbf8\ub828\ud55c \ud589\ub3d9\uc774\uba74\uc11c \uc8c4\ucc45\uac10\uc774 \ub4e4\uc5b4.", "offset": 26, "length": 31, "sentiment": "negative", "confidence": {"negative": 0.9992186, "positive": 0.0003346607, "neutral": 0.00044666594}, "highlights": [{"offset": 13, "length": 17}]}]}