{"document": {"sentiment": "negative", "confidence": {"negative": 85.918755, "positive": 0.01636287, "neutral": 14.06488}}, "sentences": [{"content": "\uc5c4\ub9c8\uac00 \uc790\uafb8\ub9cc \ub098\ud55c\ud14c \uc5c4\ub9c8\ub97c \uc5bc\ub9c8\ub098 \ubbff\ub290\ub0d0\uace0 \ubb3c\uc5b4\ubcf4\uc2dc\ub354\ub77c?", "offset": 0, "length": 32, "sentiment": "neutral", "confidence": {"negative": 0.019391885, "positive": 0.00085797184, "neutral": 0.97975016}, "highlights": [{"offset": 8, "length": 17}]}, {"content": " \ub108\ubb34 \ub72c\uae08\uc5c6\uc5c8\uc5b4.", "offset": 32, "length": 10, "sentiment": "negative", "confidence": {"negative": 0.99492115, "positive": 0.00028742905, "neutral": 0.004791488}, "highlights": [{"offset": 1, "length": 8}]}]}