{"document": {"sentiment": "positive", "confidence": {"negative": 0.043081954, "positive": 99.94639, "neutral": 0.010531792}}, "sentences": [{"content": "\uc2e4\uc218\ub85c \uc5b8\ub2c8 \uc5bc\uad74\uc5d0 \uc0c1\ucc98\ub97c \ub0c8\uc9c0\ub9cc \uc5b8\ub2c8\uac00 \ud654\ub97c \ub0b4\uc9c0 \uc54a\uc544\uc11c \uae30\ubee4\uc5b4.", "offset": 0, "length": 37, "sentiment": "positive", "confidence": {"negative": 0.0025849172, "positive": 0.99678314, "neutral": 0.00063190755}, "highlights": [{"offset": 19, "length": 17}]}]}