{"document": {"sentiment": "negative", "confidence": {"negative": 99.993195, "positive": 0.0024981438, "neutral": 0.004308403}}, "sentences": [{"content": "\uac00\uace0 \uc2f6\uc5c8\ub358 \ub300\ud559\uc5d0 \ud569\uaca9\ud588\uc9c0\ub9cc \ubabb \uac08 \uac83 \uac19\uc544.", "offset": 0, "length": 26, "sentiment": "negative", "confidence": {"negative": 0.99995637, "positive": 3.0535826e-05, "neutral": 1.3068588e-05}, "highlights": [{"offset": 0, "length": 17}]}, {"content": " \ub9c8\uc74c\uc774 \uc544\ud30c.", "offset": 26, "length": 8, "sentiment": "negative", "confidence": {"negative": 0.9992268, "positive": 0.00026924143, "neutral": 0.00050393975}, "highlights": [{"offset": 1, "length": 6}]}]}