{"document": {"sentiment": "negative", "confidence": {"negative": 85.71144, "positive": 0.008021194, "neutral": 14.280539}}, "sentences": [{"content": "\uc6b0\ub9ac \uc9d1\uc774 \uace7 \uc774\uc0ac\ub97c \uac00\uac8c \ub410\ub2e4\uace0 \ud558\ub124.", "offset": 0, "length": 22, "sentiment": "neutral", "confidence": {"negative": 0.0001600482, "positive": 0.00041239482, "neutral": 0.9994276}, "highlights": [{"offset": 8, "length": 11}]}, {"content": " \uc9c0\uae08 \ub108\ubb34 \uba38\ub9ac\uac00 \uc544\ud30c.", "offset": 22, "length": 14, "sentiment": "negative", "confidence": {"negative": 0.9996408, "positive": 0.00014908871, "neutral": 0.00021005956}, "highlights": [{"offset": 4, "length": 9}]}]}